bin/__init__.py
python_bin-0.0.3.dist-info/METADATA
python_bin-0.0.3.dist-info/WHEEL
python_bin-0.0.3.dist-info/top_level.txt
python_bin-0.0.3.dist-info/RECORD
