Metadata-Version: 2.4
Name: python-bin
Version: 0.0.3
Summary: Self-explanatory
Author-email: Jason Wilkes <notarealdeveloper@gmail.com>
Project-URL: source, https://github.com/notarealdeveloper/python-bin
